{
  "resourceType": "DiagnosticReport",
  "identifier": [
      {
          "system": "http://sys-ids.kemkes.go.id/diagnostic/{{Org_id}}/lab",
          "value": "{{Identifier_value}}"
      }
  ],
  "status": "final",
  "category": [
      {
          "coding": [
              {
                  "system": "http://terminology.hl7.org/CodeSystem/v2-0074",
                  "code": "CH",
                  "display": "Chemistry"
              }
          ]
      }
  ],
  "code": {
      "coding": [
          {
              "system": "http://loinc.org",
              "code": "4548-4",
              "display": "Hemoglobin A1c/Hemoglobin.total in Blood"
          }
      ]
  },
  "subject": {
      "reference": "Patient/{{Patient_ptm_id}}"
  },
  "encounter": {
      "reference": "Encounter/{{Encounter_ptm_uuid}}"
  },
  "effectiveDateTime": "2024-04-24T02:43:35+00:00",
  "issued": "2024-04-24T02:43:35+00:00",
  "performer": [
      {
          "reference": "Practitioner/{{Practitioner_ID}}"
      },
      {
          "reference": "Organization/{{Org_id}}"
      }
  ],
  "result": [
      {
          "reference": "Observation/{{Observation_Hba1c}}"
      }
  ],
  "specimen": [
      {
          "reference": "Specimen/{{Specimen_DiabetesPanel}}"
      }
  ],
  "basedOn": [
      {
          "reference": "ServiceRequest/{{ServiceRequest_Hba1c}}"
      }
  ],
  "conclusionCode": [
      {
          "coding": [
              {
                  "system": "http://terminology.hl7.org/CodeSystem/v3-ObservationInterpretation",
                  "code": "N",
                  "display": "Normal"
              }
          ]
      }
  ]
}

{
  "basedOn": [
      {
          "reference": "ServiceRequest/4cf81f3c-539e-4c6d-81e0-ce7ea28f050c"
      }
  ],
  "category": [
      {
          "coding": [
              {
                  "code": "CH",
                  "display": "Chemistry",
                  "system": "http://terminology.hl7.org/CodeSystem/v2-0074"
              }
          ]
      }
  ],
  "code": {
      "coding": [
          {
              "code": "4548-4",
              "display": "Hemoglobin A1c/Hemoglobin.total in Blood",
              "system": "http://loinc.org"
          }
      ]
  },
  "conclusionCode": [
      {
          "coding": [
              {
                  "code": "N",
                  "display": "Normal",
                  "system": "http://terminology.hl7.org/CodeSystem/v3-ObservationInterpretation"
              }
          ]
      }
  ],
  "effectiveDateTime": "2024-04-24T02:43:35+00:00",
  "encounter": {
      "reference": "Encounter/6c53b3ee-7612-4c94-baac-796af15bcebc"
  },
  "id": "4f211659-b7c8-49c7-879d-3a1d53e15922",
  "identifier": [
      {
          "system": "http://sys-ids.kemkes.go.id/diagnostic/8529d474-30e0-4fee-81a4-7a5234003a1b/lab",
          "value": "2024082985902A069"
      }
  ],
  "issued": "2024-04-24T02:43:35+00:00",
  "meta": {
      "lastUpdated": "2024-08-29T08:04:53.227607+00:00",
      "versionId": "MTcyNDkxODY5MzIyNzYwNzAwMA"
  },
  "performer": [
      {
          "reference": "Practitioner/10009880728"
      },
      {
          "reference": "Organization/8529d474-30e0-4fee-81a4-7a5234003a1b"
      }
  ],
  "resourceType": "DiagnosticReport",
  "result": [
      {
          "reference": "Observation/5591dc7f-b2e2-4836-9294-cff6cfd69a22"
      }
  ],
  "specimen": [
      {
          "reference": "Specimen/7798713c-f74d-4306-9f4a-1b65aaac9c90"
      }
  ],
  "status": "final",
  "subject": {
      "reference": "Patient/P02029555482"
  }
}