{
  "resourceType": "Observation",
  "status": "final",
  "category": [
      {
          "coding": [
              {
                  "system": "http://terminology.hl7.org/CodeSystem/observation-category",
                  "code": "imaging",
                  "display": "Imaging"
              }
          ]
      }
  ],
  "code": {
      "coding": [
          {
              "system": "http://loinc.org",
              "code": "11850-5",
              "display": "Gestational sac Mean diameter US"
          },
          {
              "system": "http://terminology.kemkes.go.id/CodeSystem/anc-custom-codes",
              "code": "ANC.SS.DE36",
              "display": "Gestational sac (GS) USG"
          }
      ]
  },
  "subject": {
      "reference": "Patient/{{Patient_Ibu_ID}}",
      "display": "{{Patient_Ibu_name}}"
  },
  "encounter": {
      "reference": "Encounter/{{Encounter_ANC_uuid}}"
  },
  "effectiveDateTime": "2015-06-20T04:55:00+00:00",
  "issued": "2015-06-20T04:55:00+00:00",
  "performer": [
      {
          "reference": "Practitioner/{{Performer_id}}"
      }
  ],
  "valueQuantity": {
      "value": 3.21,
      "unit": "cm",
      "system": "http://unitsofmeasure.org",
      "code": "cm"
  },
  "basedOn" : [
      {
          "reference" : "ServiceRequest/{{ServiceRequest_Rad_ANC_uuid}}"
      }
  ]
}

{
  "basedOn": [
      {
          "reference": "ServiceRequest/76e5e660-3da9-4eaf-9d46-e6b26db55bf9"
      }
  ],
  "category": [
      {
          "coding": [
              {
                  "code": "imaging",
                  "display": "Imaging",
                  "system": "http://terminology.hl7.org/CodeSystem/observation-category"
              }
          ]
      }
  ],
  "code": {
      "coding": [
          {
              "code": "11850-5",
              "display": "Gestational sac Mean diameter US",
              "system": "http://loinc.org"
          },
          {
              "code": "ANC.SS.DE36",
              "display": "Gestational sac (GS) USG",
              "system": "http://terminology.kemkes.go.id/CodeSystem/anc-custom-codes"
          }
      ]
  },
  "effectiveDateTime": "2015-06-20T04:55:00+00:00",
  "encounter": {
      "reference": "Encounter/91d80ec6-b848-4580-873b-3d2b3dc01ce1"
  },
  "id": "0d024621-a0a1-4246-9502-85f07d9b9505",
  "identifier": [],
  "issued": "2015-06-20T04:55:00+00:00",
  "meta": {
      "lastUpdated": "2024-08-27T12:21:02.106924+00:00",
      "versionId": "MTcyNDc2MTI2MjEwNjkyNDAwMA"
  },
  "performer": [
      {
          "reference": "Practitioner/10006926841"
      }
  ],
  "resourceType": "Observation",
  "status": "final",
  "subject": {
      "display": "Diana Rose",
      "reference": "Patient/P02029552358"
  },
  "valueQuantity": {
      "code": "cm",
      "system": "http://unitsofmeasure.org",
      "unit": "cm",
      "value": 3.21
  }
}